nasty/__init__.py
nasty/__main__.py
nasty/_cli.py
nasty/_settings.py
nasty/_version.py
nasty/py.typed
nasty/_retriever/__init__.py
nasty/_retriever/conversation_retriever.py
nasty/_retriever/replies_retriever.py
nasty/_retriever/retriever.py
nasty/_retriever/search_retriever.py
nasty/_retriever/thread_retriever.py
nasty/_util/__init__.py
nasty/_util/argparse_.py
nasty/_util/consts.py
nasty/_util/errors.py
nasty/_util/io_.py
nasty/_util/json_.py
nasty/_util/time_.py
nasty/_util/tweepy_.py
nasty/_util/typing_.py
nasty/batch/__init__.py
nasty/batch/_execute_result.py
nasty/batch/batch.py
nasty/batch/batch_entry.py
nasty/batch/batch_results.py
nasty/request/__init__.py
nasty/request/conversation_request.py
nasty/request/replies.py
nasty/request/request.py
nasty/request/search.py
nasty/request/thread.py
nasty/tweet/__init__.py
nasty/tweet/conversation_tweet_stream.py
nasty/tweet/tweet.py
nasty/tweet/tweet_stream.py
nasty-0.2.7.dist-info/LICENSE
nasty-0.2.7.dist-info/METADATA
nasty-0.2.7.dist-info/WHEEL
nasty-0.2.7.dist-info/entry_points.txt
nasty-0.2.7.dist-info/top_level.txt
nasty-0.2.7.dist-info/zip-safe
nasty-0.2.7.dist-info/RECORD
