Metadata-Version: 2.1
Name: nasty
Version: 0.2.7
Summary: NASTY Advanced Search Tweet Yielder
Home-page: UNKNOWN
Author: Lukas Schmelzeisen
Author-email: me@lschmelzeisen.com
License: Apache License, Version 2.0
Project-URL: Repository, https://github.com/lschmelzeisen/nasty
Project-URL: Issue Tracker, https://github.com/lschmelzeisen/nasty/issues
Keywords: python,twitter,crawler
Platform: any
Classifier: Development Status :: 4 - Beta
Classifier: Environment :: Console
Classifier: Intended Audience :: Science/Research
Classifier: License :: OSI Approved :: Apache Software License
Classifier: Natural Language :: English
Classifier: Operating System :: OS Independent
Classifier: Programming Language :: Python
Classifier: Programming Language :: Python :: 3
Classifier: Programming Language :: Python :: 3.6
Classifier: Programming Language :: Python :: 3.7
Classifier: Programming Language :: Python :: 3.8
Classifier: Programming Language :: Python :: 3 :: Only
Classifier: Programming Language :: Python :: Implementation :: PyPy
Classifier: Topic :: Internet
Classifier: Topic :: Scientific/Engineering
Classifier: Topic :: Sociology
Classifier: Typing :: Typed
Requires-Python: >=3.6
Requires-Dist: more-itertools (~=8.5)
Requires-Dist: nasty-utils (~=0.1)
Requires-Dist: overrides (~=3.1)
Requires-Dist: requests (~=2.24)
Requires-Dist: tweepy (~=3.9)
Requires-Dist: typing-extensions (~=3.7)
Provides-Extra: dev
Requires-Dist: autoflake (~=1.4) ; extra == 'dev'
Requires-Dist: black (==20.8b1) ; extra == 'dev'
Requires-Dist: flake8 (~=3.8) ; extra == 'dev'
Requires-Dist: flake8-bandit (~=2.1) ; extra == 'dev'
Requires-Dist: flake8-bugbear (~=20.1) ; extra == 'dev'
Requires-Dist: flake8-builtins (~=1.5) ; extra == 'dev'
Requires-Dist: flake8-comprehensions (~=3.2) ; extra == 'dev'
Requires-Dist: flake8-eradicate (~=0.4) ; extra == 'dev'
Requires-Dist: flake8-print (~=3.1) ; extra == 'dev'
Requires-Dist: flake8-pyi (~=20.5) ; extra == 'dev'
Requires-Dist: isort (~=5.5) ; extra == 'dev'
Requires-Dist: licenseheaders (~=0.8) ; extra == 'dev'
Requires-Dist: mypy (~=0.782) ; extra == 'dev'
Requires-Dist: nasty-typeshed (~=0.1) ; extra == 'dev'
Requires-Dist: nox (~=2020.8) ; extra == 'dev'
Requires-Dist: pep8-naming (~=0.11) ; extra == 'dev'
Requires-Dist: twine (~=3.2) ; extra == 'dev'
Requires-Dist: vulture (~=2.1) ; extra == 'dev'
Provides-Extra: test
Requires-Dist: coverage[toml] (~=5.3) ; extra == 'test'
Requires-Dist: pytest (~=6.0) ; extra == 'test'
Requires-Dist: pytest-cov (~=2.10) ; extra == 'test'
Requires-Dist: pytest-html (~=2.1) ; extra == 'test'
Requires-Dist: responses (~=0.12) ; extra == 'test'
